{"analysisResults":[[{"matchingRatio":0.00013224283854166666,"averageDistanceRatio":0.11631888241859355,"mismatchingAverageDistanceRatio":0.11633426679225382},{"matchingRatio":0.007303873697916667,"averageDistanceRatio":0.11629057621048056,"mismatchingAverageDistanceRatio":0.11717459422922684},{"matchingRatio":0.1892242431640625,"averageDistanceRatio":0.1138271620250243,"mismatchingAverageDistanceRatio":0.1432326017955566}],[{"matchingRatio":0.000020345052083333332,"averageDistanceRatio":0.1377639933933861,"mismatchingAverageDistanceRatio":0.13776679626603147},{"matchingRatio":0.0005069308810763889,"averageDistanceRatio":0.13773560327513887,"mismatchingAverageDistanceRatio":0.1378338581088801},{"matchingRatio":0.16013929578993055,"averageDistanceRatio":0.13520017923235408,"mismatchingAverageDistanceRatio":0.16381898824144533}]],"lighting":"../../../shared-assets/environments/lightroom_14b.hdr","dimensions":{"width":768,"height":768},"target":{"x":0,"y":10,"z":0},"orbit":{"theta":0,"phi":70,"radius":0},"verticalFoV":45,"name":"khronos-VC","model":"../../../shared-assets/models/glTF-Sample-Models/2.0/VC/glTF-Binary/VC.glb"}